{"job_id":"clone_1760983506_68f679d2e599b","feed_url":"http:\/\/localhost:8000\/self-hosted-feed.php?id=shp_1760983511_68f679d7b54df","options":{"download_episode_images":true,"import_to_directory":false,"limit_episodes":0},"phase":"complete","message":"Cloning complete!","percent":100,"started_at":1760983506,"updated_at":1760983524,"podcast_id":"shp_1760983511_68f679d7b54df","current_episode":5,"total_episodes":5,"episode_title":"Wednesday, October 15, 2025 - 2025 Nobel Peace Prize Recipient, Maria Corina Machado","action":"downloading_audio","episodes_cloned":1,"episodes_failed":4}